geosdemo/__init__.py
geosdemo/foliumap.py
geosdemo/geosdemo.py
geosdemo-0.1.0.dist-info/LICENSE
geosdemo-0.1.0.dist-info/METADATA
geosdemo-0.1.0.dist-info/WHEEL
geosdemo-0.1.0.dist-info/dependency_links.txt
geosdemo-0.1.0.dist-info/top_level.txt
geosdemo-0.1.0.dist-info/RECORD
