Metadata-Version: 2.1
Name: geosdemo
Version: 0.1.0
Summary: A python package for interactive mapping.
Home-page: https://github.com/giswqs/geosdemo
Author: Qiusheng Wu
Author-email: giswqs@gmail.com
License: MIT license
Keywords: geosdemo
Classifier: Development Status :: 2 - Pre-Alpha
Classifier: Intended Audience :: Developers
Classifier: License :: OSI Approved :: MIT License
Classifier: Natural Language :: English
Classifier: Programming Language :: Python :: 3
Classifier: Programming Language :: Python :: 3.7
Classifier: Programming Language :: Python :: 3.8
Classifier: Programming Language :: Python :: 3.9
Classifier: Programming Language :: Python :: 3.10
Requires-Python: >=3.7
License-File: LICENSE
Requires-Dist: folium
Requires-Dist: ipyleaflet
Requires-Dist: geopandas
Requires-Dist: httpx
